{
  "@id": "dtmi:org:brickschema:schema:Brick:Coldest_Zone_Air_Temperature_Sensor;1",
  "@type": "Interface",
  "contents": [
    {
      "@type": "Property",
      "description": {
        "en": "Brick tags associated with this interface."
      },
      "displayName": {
        "en": "Tags"
      },
      "name": "tags",
      "schema": {
        "@type": "Map",
        "mapKey": {
          "name": "tagName",
          "schema": "string"
        },
        "mapValue": {
          "name": "tagValue",
          "schema": "boolean"
        }
      }
    }
  ],
  "description": {
    "en": "The zone temperature that is coldest; drives the supply temperature of hot air. A computed value rather than a physical sensor. Also referred to as a 'Lowest Zone Air Temperature Sensor'"
  },
  "displayName": {
    "en": "Coldest Zone Air Temperature Sensor"
  },
  "extends": "dtmi:org:brickschema:schema:Brick:Zone_Air_Temperature_Sensor;1",
  "@context": [
    "dtmi:dtdl:context;2"
  ]
}