{
  "@id": "dtmi:org:brickschema:schema:Brick:Lead_Lag_Command;1",
  "@type": "Interface",
  "contents": [
    {
      "@type": "Property",
      "description": {
        "en": "Brick tags associated with this interface."
      },
      "displayName": {
        "en": "Tags"
      },
      "name": "tags",
      "schema": {
        "@type": "Map",
        "mapKey": {
          "name": "tagName",
          "schema": "string"
        },
        "mapValue": {
          "name": "tagValue",
          "schema": "boolean"
        }
      }
    }
  ],
  "displayName": {
    "en": "Lead Lag Command"
  },
  "extends": "dtmi:org:brickschema:schema:Brick:Command;1",
  "@context": [
    "dtmi:dtdl:context;2"
  ]
}